
<?xml version="1.0" encoding="UTF-8"?>

<!--
	====================== Hooks XML file for parabot. ======================
	
	========== CHANGELOG ==========
	
	===Changelog parabot v2.01
	> New constants
	> Added a RSImageProducer getter
	> Added <invokers>...</invokers>
	> Added <callbacks>...</callbacks>
	
	===Changelog parabot v2.00
	> Initial release
	
	===============================

-->

<injector>
	<interfaces>
		<add>
			<classname>client</classname>
			<interface>Client</interface>
		</add>
		<add>
			<classname>LI</classname>
			<interface>Node</interface>
		</add>
		<add>
			<classname>CZ</classname>
			<interface>Player</interface>
		</add>
		<add>
			<classname>BZ</classname>
			<interface>RSApplet</interface>
		</add>
		<add>
			<classname>ZI</classname>
			<interface>Character</interface>
		</add>
		<add>
			<classname>CI</classname>
			<interface>NpcDef</interface>
		</add>
		<add>
			<classname>KI</classname>
			<interface>Npc</interface>
		</add>
		<add>
			<classname>Model</classname>
			<interface>Model</interface>
		</add>
		<add>
			<classname>vI</classname>
			<interface>Scene</interface>
		</add>
		<add>
			<classname>Ground</classname>
			<interface>SceneTile</interface>
		</add>
		<add>
			<classname>QI</classname>
			<interface>SceneObjectTile</interface>
		</add>
		<add>
			<classname>RI</classname>
			<interface>SceneObjectTile</interface>
		</add>
		<add>
			<classname>TI</classname>
			<interface>SceneObjectTile</interface>
		</add>
		<add>
			<classname>WI</classname>
			<interface>SceneObjectTile</interface>
		</add>
		<add>
			<classname>VI</classname>
			<interface>SceneObjectTile</interface>
		</add>
		<add>
			<classname>zI</classname>
			<interface>Renderable</interface>
		</add>
		<add>
			<classname>NI</classname>
			<interface>Deque</interface>
		</add>
		<add>
			<classname>SI</classname>
			<interface>GroundItem</interface>
		</add>
		<add>
			<classname>JZ</classname>
			<interface>Interface</interface>
		</add>
		<add>
			<classname>E</classname>
			<interface>CollisionMap</interface>
		</add>
		<!-- ======= since parabot v2.01 ======= -->
		<add>
			<classname>AI</classname>
			<interface></interface>
		</add>
		<add>
			<classname>WI</classname>
			<interface>ObjectDef</interface>
		</add>
		
		<!-- ======= end since parabot v2.01 ======= -->
	</interfaces>	
	<getters>
		<!-- CLIENT HOOKS -->
		<add>
			<accessor>Client</accessor>
			<field>vI</field>
			<methodname>getScene</methodname>
			<desc>%sScene</desc>
		</add>
		<add>
			<accessor>Client</accessor>
			<field>trim</field>
			<methodname>getNPCCount</methodname>
		</add>
		<add>
			<accessor>Client</accessor>
			<field>ID</field>
			<methodname>isLoggedIn</methodname>
		</add>
		<add>
			<accessor>Client</accessor>
			<field>CF</field>
			<methodname>getUsername</methodname>
		</add>
		
		<add>
			<accessor>Client</accessor>
			<field>MD</field>
			<methodname>getLocalPlayer</methodname>
			<desc>%sPlayer</desc>
		</add>
		
		<add>
			<accessor>Client</accessor>
			<field>a</field>
			<methodname>getCameraX</methodname>
		</add>
		
		<add>
			<accessor>Client</accessor>
			<field>g</field>
			<methodname>getCameraY</methodname>
		</add>
		
		<add>
			<accessor>Client</accessor>
			<field>e</field>
			<methodname>getCameraZ</methodname>
		</add>
		
		<add>
			<accessor>Client</accessor>
			<field>h</field>
			<methodname>getCameraYaw</methodname>
		</add>
		
		<add>
			<accessor>Client</accessor>
			<field>k</field>
			<methodname>getCameraPitch</methodname>
		</add>
		
		<add>
			<accessor>Client</accessor>
			<field>zI</field>
			<methodname>getPlane</methodname>
		</add>
		
		<add>
			<accessor>Client</accessor>
			<field>FJ</field>
			<methodname>getSceneFlags</methodname>
		</add>
		
		<add>
			<accessor>Client</accessor>
			<field>pF</field>
			<methodname>getTileOffsets</methodname>
		</add>
		
		<add>
			<accessor>Client</accessor>
			<field>aC</field>
			<methodname>getBaseY</methodname>
		</add>
		<add>
			<accessor>Client</accessor>
			<field>eC</field>
			<methodname>getBaseX</methodname>
		</add>
		<add>
			<accessor>Client</accessor>
			<field>HI</field>
			<methodname>getPlayerIndices</methodname>
		</add>
		<add>
			<accessor>Client</accessor>
			<field>ValueOf</field>
			<methodname>getNpcIndices</methodname>
		</add>
		<add>
			<accessor>Client</accessor>
			<field>totalMemory</field>
			<methodname>getNpcs</methodname>
			<desc>[%sNpc</desc>
		</add>
		<add>
			<accessor>Client</accessor>
			<field>playerArray</field>
			<methodname>getPlayers</methodname>
			<desc>[%sPlayer</desc>
		</add>
		<add>
			<accessor>Client</accessor>
			<field>sin</field>
			<methodname>getGroundItems</methodname>
			<desc>[[[%sDeque</desc>
		</add>
		<add>
			<accessor>Client</accessor>
			<field>crossType</field>
			<methodname>getCrosshairType</methodname>
		</add>
		<add>
			<accessor>Client</accessor>
			<field>menuActionRow</field>
			<methodname>getMenuActionRow</methodname>
		</add>
		<add>
			<accessor>Client</accessor>
			<field>menuActionName</field>
			<methodname>getMenuActions</methodname>
		</add>
		<add>
			<accessor>Client</accessor>
			<field>menuOffsetX</field>
			<methodname>getMenuOffsetX</methodname>
		</add>
		<add>
			<accessor>Client</accessor>
			<field>menuOffsetY</field>
			<methodname>getMenuOffsetY</methodname>
		</add>
		<add>
			<accessor>Client</accessor>
			<field>menuScreenArea</field>
			<methodname>getMenuScreenArea</methodname>
		</add>
		<add>
			<accessor>Client</accessor>
			<field>menuOpen</field>
			<methodname>isMenuOpen</methodname>
		</add>
		<add>
			<accessor>Client</accessor>
			<field>menuWidth</field>
			<methodname>getMenuWidth</methodname>
		</add>
		<add>
			<accessor>Client</accessor>
			<field>menuHeight</field>
			<methodname>getMenuHeight</methodname>
		</add>
		<add>
			<accessor>Client</accessor>
			<field>backDialogID</field>
			<methodname>getChatboxInterfaceId</methodname>
		</add>
		<add>
			<accessor>Client</accessor>
			<field>openInterfaceID</field>
			<methodname>getOpenInterfaceId</methodname>
		</add>
		<add>
			<accessor>Client</accessor>
			<field>tabID</field>
			<methodname>getOpenTab</methodname>
		</add>
		<add>
			<accessor>Client</accessor>
			<field>currentExp</field>
			<methodname>getCurrentExp</methodname>
		</add>
		<add>
			<accessor>Client</accessor>
			<field>currentStats</field>
			<methodname>getCurrentStats</methodname>
		</add>
		<add>
			<accessor>Client</accessor>
			<field>minimapInt1</field>
			<methodname>getMinimapInt1</methodname>
		</add>
		<add>
			<accessor>Client</accessor>
			<field>minimapInt2</field>
			<methodname>getMinimapInt2</methodname>
		</add>
		<add>
			<accessor>Client</accessor>
			<field>minimapInt3</field>
			<methodname>getMinimapInt3</methodname>
		</add>
		<add>
			<accessor>Client</accessor>
			<field>destX</field>
			<methodname>getDestinationX</methodname>
		</add>
		<add>
			<accessor>Client</accessor>
			<field>destY</field>
			<methodname>getDestinationY</methodname>
		</add>
		<add>
			<accessor>Client</accessor>
			<field>aClass11Array1230</field>
			<methodname>getCollisionMap</methodname>
			<desc>[%sCollisionMap</desc>
		</add>
		<add>
			<accessor>Client</accessor>
			<field>loopCycle</field>
			<methodname>getLoopCycle</methodname>
		</add>
		<!-- NODE HOOKS -->
		<add>
			<accessor>Node</accessor>
			<field>prev</field>
			<methodname>getPrevious</methodname>
			<desc>%sNode</desc>
		</add>
		
		<add>
			<accessor>Node</accessor>
			<field>next</field>
			<methodname>getNext</methodname>
			<desc>%sNode</desc>
		</add>
		
		<add>
			<accessor>Node</accessor>
			<field>id</field>
			<methodname>getId</methodname>
		</add>
		<!-- PLAYER HOOKS -->
		<add>
			<accessor>Player</accessor>
			<field>name</field>
			<methodname>getName</methodname>
		</add>
		<!-- CHARACTER HOOKS -->
		<add>
			<accessor>Character</accessor>
			<field>smallX</field>
			<methodname>getQueueX</methodname>
		</add>
		<add>
			<accessor>Character</accessor>
			<field>smallY</field>
			<methodname>getQueueY</methodname>
		</add>
		<add>
			<accessor>Character</accessor>
			<field>interactingEntity</field>
			<methodname>getInteractingId</methodname>
		</add>
		<add>
			<accessor>Character</accessor>
			<field>x</field>
			<methodname>getX</methodname>
		</add>
		<add>
			<accessor>Character</accessor>
			<field>y</field>
			<methodname>getY</methodname>
		</add>
		<add>
			<accessor>Character</accessor>
			<field>height</field>
			<methodname>getHeight</methodname>
		</add>
		<add>
			<accessor>Character</accessor>
			<field>turnDirection</field>
			<methodname>getTurnDirection</methodname>
		</add>
		<add>
			<accessor>Character</accessor>
			<field>smallXYIndex</field>
			<methodname>isWalking</methodname>
		</add>
		<add>
			<accessor>Character</accessor>
			<field>anim</field>
			<methodname>getAnimation</methodname>
		</add>
		<add>
			<accessor>Character</accessor>
			<field>currentHealth</field>
			<methodname>getHealth</methodname>
		</add>
		<add>
			<accessor>Character</accessor>
			<field>maxHealth</field>
			<methodname>getMaxHealth</methodname>
		</add>
		<add>
			<accessor>Character</accessor>
			<field>textSpoken</field>
			<methodname>getDisplayedText</methodname>
		</add>
		<add>
			<accessor>Character</accessor>
			<field>loopCycleStatus</field>
			<methodname>getLoopCycleStatus</methodname>
		</add>
		<!-- NPC Hooks -->
		<add>
			<accessor>Npc</accessor>
			<field>desc</field>
			<methodname>getDef</methodname>
			<desc>%sNpcDef</desc>
		</add>
		<!-- NPCDef Hooks -->
		<add>
			<accessor>NpcDef</accessor>
			<field>name</field>
			<methodname>getName</methodname>
		</add>
		<add>
			<accessor>NpcDef</accessor>
			<field>actions</field>
			<methodname>getActions</methodname>
		</add>
		<add>
			<accessor>NpcDef</accessor>
			<field>combatLevel</field>
			<methodname>getLevel</methodname>
		</add>
		<add>
			<accessor>NpcDef</accessor>
			<field>type</field>
			<methodname>getId</methodname>
			<desc>I</desc>
		</add>
		<!-- MODEL HOOKS -->
		<add>
			<accessor>Model</accessor>
			<field>anInt1630</field>
			<methodname>getTexturedTriangleCount</methodname>
		</add>
		<add>
			<accessor>Model</accessor>
			<field>anIntArray1633</field>
			<methodname>getTriangleC</methodname>
		</add>
		<add>
			<accessor>Model</accessor>
			<field>anIntArray1632</field>
			<methodname>getTriangleB</methodname>
		</add>
		<add>
			<accessor>Model</accessor>
			<field>anIntArray1631</field>
			<methodname>getTriangleA</methodname>
		</add>
		<add>
			<accessor>Model</accessor>
			<field>anInt1626</field>
			<methodname>getVertexCount</methodname>
		</add>
		<add>
			<accessor>Model</accessor>
			<field>anIntArray1629</field>
			<methodname>getVertexZ</methodname>
		</add>
		<add>
			<accessor>Model</accessor>
			<field>anIntArray1628</field>
			<methodname>getVertexY</methodname>
		</add>
		<add>
			<accessor>Model</accessor>
			<field>anIntArray1627</field>
			<methodname>getVertexX</methodname>
		</add>
		<!-- Scene hooks -->
		<add>
			<accessor>Scene</accessor>
			<field>groundArray</field>
			<methodname>getSceneTiles</methodname>
			<desc>[[[%sSceneTile</desc>
		</add>
		<!-- SceneTile hooks -->
		<add>
			<accessor>SceneTile</accessor>
			<field>obj1</field>
			<methodname>getWallObject</methodname>
			<desc>%sSceneObjectTile</desc>
		</add>
		<add>
			<accessor>SceneTile</accessor>
			<field>obj2</field>
			<methodname>getWallDecoration</methodname>
			<desc>%sSceneObjectTile</desc>
		</add>
		<add>
			<accessor>SceneTile</accessor>
			<field>obj3</field>
			<methodname>getGroundDecoration</methodname>
			<desc>%sSceneObjectTile</desc>
		</add>
		<add>
			<accessor>SceneTile</accessor>
			<field>obj4</field>
			<methodname>getGroundItem</methodname>
			<desc>%sSceneObjectTile</desc>
		</add>
		<add>
			<accessor>SceneTile</accessor>
			<field>obj5Array</field>
			<methodname>getInteractiveObjects</methodname>
			<desc>[%sSceneObjectTile</desc>
		</add>
		<!-- Object hooks --> 
		<!-- Object 1, Walls -->
		<add>
			<classname>Object1</classname>
			<field>uid</field>
			<methodname>getHash</methodname>
		</add>
		<add>
			<classname>Object1</classname>
			<field>aClass30_Sub2_Sub4_278</field>
			<methodname>getRenderable</methodname>
			<desc>%sRenderable</desc>
		</add>
		<add>
			<classname>Object1</classname>
			<field>anInt274</field>
			<methodname>getX</methodname>
		</add>
		<add>
			<classname>Object1</classname>
			<field>anInt275</field>
			<methodname>getY</methodname>
		</add>
		<!-- Object 2, Wall decoration -->
		<add>
			<classname>Object2</classname>
			<field>uid</field>
			<methodname>getHash</methodname>
		</add>
		<add>
			<classname>Object2</classname>
			<field>aClass30_Sub2_Sub4_504</field>
			<methodname>getRenderable</methodname>
			<desc>%sRenderable</desc>
		</add>
		<add>
			<classname>Object2</classname>
			<field>anInt500</field>
			<methodname>getX</methodname>
		</add>
		<add>
			<classname>Object2</classname>
			<field>anInt501</field>
			<methodname>getY</methodname>
		</add>
		<add>
			<classname>Object2</classname>
			<field>anInt503</field>
			<methodname>getOrientation</methodname>
		</add>
		<!-- Object 3, Ground decoration -->
		<add>
			<classname>Object3</classname>
			<field>uid</field>
			<methodname>getHash</methodname>
		</add>
		<add>
			<classname>Object3</classname>
			<field>aClass30_Sub2_Sub4_814</field>
			<methodname>getRenderable</methodname>
			<desc>%sRenderable</desc>
		</add>
		<add>
			<classname>Object3</classname>
			<field>anInt812</field>
			<methodname>getX</methodname>
		</add>
		<add>
			<classname>Object3</classname>
			<field>anInt813</field>
			<methodname>getY</methodname>
		</add>
		<!-- Object 4, Grounditem -->
		<add>
			<classname>Object4</classname>
			<field>uid</field>
			<methodname>getHash</methodname>
		</add>
		<add>
			<classname>Object4</classname>
			<field>aClass30_Sub2_Sub4_49</field>
			<methodname>getRenderable</methodname>
			<desc>%sRenderable</desc>
		</add>
		<add>
			<classname>Object4</classname>
			<field>anInt46</field>
			<methodname>getX</methodname>
		</add>
		<add>
			<classname>Object4</classname>
			<field>anInt47</field>
			<methodname>getY</methodname>
		</add>
		<!-- Object 5, InteractiveObject -->
		<add>
			<classname>Object5</classname>
			<field>uid</field>
			<methodname>getHash</methodname>
		</add>
		<add>
			<classname>Object5</classname>
			<field>aClass30_Sub2_Sub4_521</field>
			<methodname>getRenderable</methodname>
			<desc>%sRenderable</desc>
		</add>
		<add>
			<classname>Object5</classname>
			<field>anInt519</field>
			<methodname>getX</methodname>
		</add>
		<add>
			<classname>Object5</classname>
			<field>anInt520</field>
			<methodname>getY</methodname>
		</add>
		<!-- Deque hooks -->
		<add>
			<accessor>Deque</accessor>
			<field>head</field>
			<methodname>getHead</methodname>
			<desc>%sNode</desc>
		</add>
		<add>
			<accessor>Deque</accessor>
			<field>current</field>
			<methodname>getCurrent</methodname>
			<desc>%sNode</desc>
		</add>
		<!-- Grounditem hooks -->
		<add>
			<accessor>GroundItem</accessor>
			<field>ID</field>
			<methodname>getId</methodname>
		</add>
		<add>
			<accessor>GroundItem</accessor>
			<field>x</field>
			<methodname>getX</methodname>
		</add>
		<add>
			<accessor>GroundItem</accessor>
			<field>y</field>
			<methodname>getY</methodname>
		</add>
		<!-- Interface hooks -->
		<add>
			<accessor>Interface</accessor>
			<field>id</field>
			<methodname>getId</methodname>
		</add>
		<add>
			<accessor>Interface</accessor>
			<field>childX</field>
			<methodname>getChildX</methodname>
		</add>
		<add>
			<accessor>Interface</accessor>
			<field>childY</field>
			<methodname>getChildY</methodname>
		</add>
		<add>
			<accessor>Interface</accessor>
			<field>children</field>
			<methodname>getChildren</methodname>
		</add>
		<add>
			<accessor>Interface</accessor>
			<field>k</field>
			<methodname>getMessage</methodname>
		</add>
		<add>
			<accessor>Interface</accessor>
			<field>o</field>
			<methodname>getItems</methodname>
		</add>
		<add>
			<accessor>Interface</accessor>
			<field>l</field>
			<methodname>isInventory</methodname>
		</add>
		<add>
			<accessor>Interface</accessor>
			<field>n</field>
			<methodname>getStackSize</methodname>
		</add>
		<add>
			<accessor>Interface</accessor>
			<field>ZI</field>
			<methodname>getHeight</methodname>
		</add>
		<add>
			<accessor>Interface</accessor>
			<field>K</field>
			<methodname>getWidth</methodname>
		</add>
		<add>
			<accessor>Interface</accessor>
			<field>L</field>
			<methodname>getTooltip</methodname>
		</add>
		<add>
			<accessor>Interface</accessor>
			<field>M</field>
			<methodname>getSelectedActionName</methodname>
		</add>
		<add>
			<accessor>Interface</accessor>
			<field>P</field>
			<methodname>getActions</methodname>
		</add>
		<add>
			<accessor>Interface</accessor>
			<field>z</field>
			<methodname>getParent</methodname>
		</add>
		<!-- Collision map -->
		<add>
			<accessor>CollisionMap</accessor>
			<field>anIntArrayArray294</field>
			<methodname>getFlags</methodname>
		</add>
		
		<!-- ======= since parabot v2.01 ======= -->
		
		<!-- RSImageProducer -->
		<add>
			<classname>RSImageProducer</classname>
			<field>anImage320</field>
			<methodname>getImage</methodname>
		</add>
		
		<!-- ItemDef -->
		<add>
			<accessor>ItemDef</accessor>
			<field>name</field>
			<methodname>getName</methodname>
		</add>
		
		<!-- ObjectDef -->
		<add>
			<accessor>ObjectDef</accessor>
			<field>name</field>
			<methodname>getName</methodname>
		</add>
		
		<!-- ======= end since parabot v2.01 ======= -->
		
		<!-- special hooks -->
		<add>
			<accessor>Interface</accessor>
			<into>client</into>
			<field>interfaceCache</field>
			<methodname>getInterfaceCache</methodname>
			<desc>[%sInterface</desc>
		</add>
	</getters>
	<!-- INVOKERS INJECTOR -->
	<invokers>
		<add>
			<accessor>Renderable</accessor>
			<methodname>getModel</methodname>
			<invokemethod>getRotatedModel</invokemethod>
			<desc>%sModel</desc>
			<argsdesc>()</argsdesc>
		</add>
		<add>
			<accessor>ItemDef</accessor>
			<into>client</into>
			<methodname>getItem</methodname>
			<invokemethod>forID</invokemethod>
			<desc>%sItemDef</desc>
			<argsdesc>(I)</argsdesc>
		</add>
		<add>
			<accessor>ObjectDef</accessor>
			<into>client</into>
			<methodname>getObjectDef</methodname>
			<invokemethod>forID</invokemethod>
			<desc>%sObjectDef</desc>
			<argsdesc>(I)</argsdesc>
		</add>
	</invokers>
	<!-- CALLBACKS INJECTOR -->
	<callbacks>
		<add>
			<accessor>Client</accessor>
			<methodname>pushMessage</methodname>
			<desc>(Ljava/lang/String;ILjava/lang/String;)V</desc>
			<callclass>org/rev317/core/MessageDispatcher</callclass>
			<callmethod>messageListenerHook</callmethod>
			<calldesc>(ILjava/lang/String;Ljava/lang/String;)V</calldesc>
			<callargs>2,3,1</callargs>
		</add>
	</callbacks>
	<!-- SUPERS INJECTOR -->
	<supers>
		<add>
			<classname>BZ</classname>
			<super>org/rev317/applet/GameApplet</super>
		</add>
		<add>
			<classname>FZ</classname>
			<super>org/rev317/painter/Painter</super>
		</add>
	</supers>
	<!-- SETTERS INJECTOR -->
	<setters>
		<add>
			<accessor>Client</accessor>
			<field>vF</field>
			<methodname>openTab</methodname>
		</add>
	</setters>
	<!-- CONSTANTS ETC. BASED ON HASHMAP<STRING,STRING> -->
	<constants>
		<add>
			<key>menuScreenOffsets</key>
			<value>4,4,516,168,5,338,516,0</value>
		</add>
		<add>
			<key>minimapX</key>
			<value>625</value>
		</add>
		<add>
			<key>minimapY</key>
			<value>85</value>
		</add>
		
		<!-- ========== since parabot v2.01: new constants, used in org/rev317/core/Injector ========== -->
		
		<!-- Used to inject painting (see Injector#injectPaint) -->
		
		<add>
			<key>ImageProducer</key>
			<value>FZ</value>
		</add>
		
		<add>
			<key>paintGraphicsName</key>
			<value>I</value>
		</add>
		
		<add>
			<key>paintGraphicsDesc</key>
			<value>(ILjava/awt/Graphics;I)V</value>
		</add>
		
		<add>
			<key>paintGraphicsImage</key>
			<value>out</value>
		</add>
		
		<!-- ========== end new constants for parabot v2.01 ========== -->
		
	</constants>
</injector>